little_t/__init__.py
little_t/account_manager.py
little_t/api_keys.py
little_t/mongo_connector.py
little_t/mongo_reader.py
little_t/mongo_writer.py
little_t/text_generation.py
little_t/tweet_collector.py
little_t/data/Tweet.py
little_t/data/User.py
little_t/data/__init__.py
little_t-0.0.6.dist-info/LICENSE
little_t-0.0.6.dist-info/METADATA
little_t-0.0.6.dist-info/WHEEL
little_t-0.0.6.dist-info/top_level.txt
little_t-0.0.6.dist-info/RECORD
